<?xml version="1.0" encoding="UTF-8" standalone="no"?><FisaCerinte><descriptionApplication><description>textul descreierei</description></descriptionApplication><domain><description>textul domeniului</description></domain><shareholders><shareholder><name>shareholder0</name><description>description shareholder0</description></shareholder><shareholder><name>shareholder1</name><description>description shareholder1</description></shareholder><shareholder><name>shareholder2</name><description>description shareholder2</description></shareholder><shareholder><name>shareholder3</name><description>description shareholder3</description></shareholder><shareholder><name>shareholder4</name><description>description shareholder4</description></shareholder></shareholders><actors><actor><name>actor0</name><description>description actor0</description></actor><actor><name>actor1</name><description>description actor1</description></actor><actor><name>actor2</name><description>description actor2</description></actor><actor><name>actor3</name><description>description actor3</description></actor><actor><name>actor4</name><description>description actor4</description></actor></actors></FisaCerinte>